Metadata-Version: 2.1
Name: mkdocs-mk2pdf-plugin
Version: 0.1.5
Summary: An MkDocs plugin to export content pages as PDF files
Home-page: https://github.com/HaoLiuHust/mkdocs-mk2pdf-plugin
Author: Liu, Hao
Author-email: haoliuhust@hotmail.com
License: MIT
Keywords: mkdocs pdf export
Platform: UNKNOWN
Classifier: Development Status :: 4 - Beta
Classifier: Intended Audience :: Developers
Classifier: Intended Audience :: Information Technology
Classifier: License :: OSI Approved :: MIT License
Classifier: Programming Language :: Python
Classifier: Programming Language :: Python :: 3 :: Only
Classifier: Programming Language :: Python :: 3.4
Classifier: Programming Language :: Python :: 3.5
Classifier: Programming Language :: Python :: 3.6
Classifier: Programming Language :: Python :: 3.7
Requires-Python: >=3.4
